river/__init__.py
river/bridge/__init__.py
river/bridge/ecog.py
river/bridge/epoch.py
river/bridge/io.py
river/bridge/normalize.py
river/bridge/pipeline.py
river/bridge/presets.py
river/bridge/spikes.py
river/bridge/splits.py
river/bridge/streaming/__init__.py
river/bridge/streaming/buffers.py
river/bridge/streaming/features.py
river/bridge/streaming/filters.py
river/bridge/streaming/normalize.py
river/bridge/streaming/pipeline.py
river/bridge/streaming/smooth.py
river_bci-0.1.0.dist-info/METADATA
river_bci-0.1.0.dist-info/WHEEL
river_bci-0.1.0.dist-info/RECORD
